keras_wrapper/__init__.py
keras_wrapper/cnn_model.py
keras_wrapper/dataset.py
keras_wrapper/model_ensemble.py
keras_wrapper/models.py
keras_wrapper/saving.py
keras_wrapper/search.py
keras_wrapper/test.py
keras_wrapper/utils.py
keras_wrapper/extra/__init__.py
keras_wrapper/extra/callbacks.py
keras_wrapper/extra/evaluation.py
keras_wrapper/extra/localization_utilities.py
keras_wrapper/extra/read_write.py
keras_wrapper/extra/regularize.py
keras_wrapper/extra/tokenizers.py
keras_wrapper/extra/nms/__init__.py
keras_wrapper/extra/nms/py_cpu_nms.py
keras_wrapper/extra/nms/setup.py
multimodal_keras_wrapper-3.1.6.dist-info/LICENSE
multimodal_keras_wrapper-3.1.6.dist-info/METADATA
multimodal_keras_wrapper-3.1.6.dist-info/WHEEL
multimodal_keras_wrapper-3.1.6.dist-info/top_level.txt
multimodal_keras_wrapper-3.1.6.dist-info/RECORD
